common_pyutil/__init__.py
common_pyutil/contexts.py
common_pyutil/decorators.py
common_pyutil/functional.py
common_pyutil/io.py
common_pyutil/log.py
common_pyutil/monitor.py
common_pyutil/net.py
common_pyutil/proc.py
common_pyutil/py.typed
common_pyutil/sqlite.py
common_pyutil/structures.py
common_pyutil/system.py
common_pyutil/venv.py
common_pyutil-0.9.0.dist-info/LICENSE.md
common_pyutil-0.9.0.dist-info/METADATA
common_pyutil-0.9.0.dist-info/WHEEL
common_pyutil-0.9.0.dist-info/entry_points.txt
common_pyutil-0.9.0.dist-info/RECORD
